dask_stitch/__init__.py
dask_stitch/local_affine.py
dask_stitch/stitch.py
dask_stitch-0.2.1.dist-info/LICENSE
dask_stitch-0.2.1.dist-info/METADATA
dask_stitch-0.2.1.dist-info/WHEEL
dask_stitch-0.2.1.dist-info/top_level.txt
dask_stitch-0.2.1.dist-info/RECORD
