Metadata-Version: 2.1
Name: dask-stitch
Version: 0.2.1
Summary: Linear blend stitching for map_overlap calls in dask
Home-page: https://github.com/GFleishman/dask_stitch
Author: Greg M. Fleishman
Author-email: greg.nli10me@gmail.com
License: MIT
Platform: UNKNOWN
Requires-Dist: numpy
Requires-Dist: dask
Requires-Dist: dask[array]
